odoo/addons/shopinvader_search_engine_product_media/README.rst
odoo/addons/shopinvader_search_engine_product_media/__init__.py
odoo/addons/shopinvader_search_engine_product_media/__manifest__.py
odoo/addons/shopinvader_search_engine_product_media/i18n/shopinvader_product_media.pot
odoo/addons/shopinvader_search_engine_product_media/i18n/shopinvader_search_engine_product_media.pot
odoo/addons/shopinvader_search_engine_product_media/models/__init__.py
odoo/addons/shopinvader_search_engine_product_media/models/se_backend.py
odoo/addons/shopinvader_search_engine_product_media/readme/CONTRIBUTORS.rst
odoo/addons/shopinvader_search_engine_product_media/readme/CREDITS.rst
odoo/addons/shopinvader_search_engine_product_media/readme/DESCRIPTION.rst
odoo/addons/shopinvader_search_engine_product_media/readme/HISTORY.rst
odoo/addons/shopinvader_search_engine_product_media/readme/USAGE.rst
odoo/addons/shopinvader_search_engine_product_media/readme/newsfragments/.gitignore
odoo/addons/shopinvader_search_engine_product_media/schemas/__init__.py
odoo/addons/shopinvader_search_engine_product_media/schemas/media_data.py
odoo/addons/shopinvader_search_engine_product_media/schemas/media_type.py
odoo/addons/shopinvader_search_engine_product_media/schemas/product_product.py
odoo/addons/shopinvader_search_engine_product_media/static/description/index.html
odoo/addons/shopinvader_search_engine_product_media/tests/__init__.py
odoo/addons/shopinvader_search_engine_product_media/tests/common.py
odoo/addons/shopinvader_search_engine_product_media/tests/test_shopinvader_search_engine_media.py
odoo/addons/shopinvader_search_engine_product_media/views/se_backend.xml
odoo_addon_shopinvader_search_engine_product_media-16.0.1.0.4.dist-info/METADATA
odoo_addon_shopinvader_search_engine_product_media-16.0.1.0.4.dist-info/WHEEL
odoo_addon_shopinvader_search_engine_product_media-16.0.1.0.4.dist-info/top_level.txt
odoo_addon_shopinvader_search_engine_product_media-16.0.1.0.4.dist-info/RECORD
