Metadata-Version: 2.1
Name: odoo-addon-shopinvader-search-engine-product-media
Version: 16.0.1.0.4
Summary: Index storage media data into search engine
Home-page: https://github.com/shopinvader/odoo-shopinvader
Author: Akretion,ACSONE SA/NV
License: AGPL-3
Platform: UNKNOWN
Classifier: Programming Language :: Python
Classifier: Framework :: Odoo
Classifier: Framework :: Odoo :: 16.0
Classifier: License :: OSI Approved :: GNU Affero General Public License v3
Classifier: Development Status :: 3 - Alpha
Requires-Python: >=3.10
Requires-Dist: odoo-addon-fs-product-multi-media <16.1dev,>=16.0dev
Requires-Dist: odoo-addon-shopinvader-product <16.1dev,>=16.0dev
Requires-Dist: odoo-addon-shopinvader-search-engine <16.1dev,>=16.0dev
Requires-Dist: odoo <16.1dev,>=16.0a
